{"id":"SOVOPSYN02565","lab_id":"99384480311","sex":"F","age":35.2,"dob":"1990-10-19","phenotype_baseline":"Burnout","phenotype_target":"Burnout","trajectory":"stable","trajectory_strength":0.0,"enrollment_date":"2025-02-12T00:00:00","n_visits_attended":12,"n_visits_with_data":12,"visit_span_days":333,"latest_visit":{"visit_num":12,"days":333,"date":"2026-01-11","biomarkers":{"m1":8.4249,"m2":9.9823,"m3":5.1408,"m4":3.0064,"m5":2.0582,"car_pct":18.4859,"aucg":73.1992,"dcs":-0.4186,"dhea":0.9142,"cor_dhea":9.2155,"da":175.3267,"dopac":2.2836,"hva":2.0335,"nor":15.6683,"epi":0.7386,"vma":1.7451,"mhpg":0.8309,"nor_epi":21.213,"hva_vma":1.1653,"ser":49.3833,"hiaa":1.7125,"hiaa_ser":0.0347,"da_ser":3.5503,"creatinine":86.8497},"result":{"score_formula":10.6,"score_displayed_patient":10.6,"tier_formula":"T1","tier_final":"T1","hpa_score":8.8,"adrenal_score":13.8,"nt_cat_score":20.7,"nt_mon_score":0.1,"nt_score":11.5,"car_pen":35.0,"m3_pen":0.0,"aucg_pen":0.0,"m1_pen":0.0,"dcs_pen":0.0,"dhea_pen":0.0,"cor_dhea_pen":23.0,"reactive_buffer":false,"da_pen":0.0,"nor_pen":0.0,"epi_pen":2.8,"nor_epi_pen":67.7,"ser_pen":0.0,"hiaa_ser_pen":0.0,"da_ser_pen":0.7,"applied_rules":[],"rule_details":[],"phenotype_flags":[],"flag_details":[],"suggested_phase":5,"phase_rationale":"consolidate gains, recovery integration","insights":[{"axis":"HPA","severity":"moderate","title":"Your morning cortisol surge is muted","body":"The normal post-waking cortisol rise is small. Often linked to chronic load, light exposure timing, or sleep architecture."},{"axis":"Neurotransmitter","severity":"moderate","title":"Sympathetic dominance signature","body":"Noradrenaline is elevated relative to adrenaline \u2014 a chronic vigilance pattern."}]}},"trajectory_data":[{"visit":2,"days":45,"month":1.5,"date":"2025-03-29","score":11.1,"tier":"T1","hpa":10.5,"adrenal":8.3,"nt":12.9},{"visit":3,"days":70,"month":2.33,"date":"2025-04-23","score":11.0,"tier":"T1","hpa":8.5,"adrenal":7.7,"nt":15.1},{"visit":4,"days":91,"month":3.03,"date":"2025-05-14","score":12.5,"tier":"T1","hpa":10.9,"adrenal":3.3,"nt":17.7},{"visit":5,"days":121,"month":4.03,"date":"2025-06-13","score":12.9,"tier":"T1","hpa":11.9,"adrenal":3.0,"nt":17.7},{"visit":7,"days":175,"month":5.83,"date":"2025-08-06","score":11.2,"tier":"T1","hpa":10.0,"adrenal":12.8,"nt":12.1},{"visit":8,"days":208,"month":6.93,"date":"2025-09-08","score":13.4,"tier":"T1","hpa":13.3,"adrenal":0.0,"nt":18.5},{"visit":10,"days":270,"month":9.0,"date":"2025-11-09","score":13.9,"tier":"T1","hpa":10.7,"adrenal":13.0,"nt":17.9},{"visit":12,"days":333,"month":11.1,"date":"2026-01-11","score":10.6,"tier":"T1","hpa":8.8,"adrenal":13.8,"nt":11.5}],"percentiles":{"m1":20.5,"m2":17.4,"m3":80.4,"m4":77.6,"m5":90.4,"car_pct":18.3,"aucg":28.5,"dcs":81.3,"dhea":39.2,"cor_dhea":25.9,"da":60.9,"dopac":66.9,"hva":31.7,"nor":18.4,"epi":6.2,"vma":68.2,"mhpg":52.6,"nor_epi":94.1,"hva_vma":17.7,"ser":36.4,"hiaa":33.1,"hiaa_ser":46.7,"da_ser":74.9,"creatinine":22.6},"score_percentile":55.7,"patterns":[{"id":"SYMPATHO_ADRENAL_EXHAUSTION","name":"Sympatho-adrenal exhaustion","tone":"warning","summary":"Chronic noradrenergic activity with adrenal-medulla EPI depletion \u2014 a fatigue signature of sustained physiological stress.","evidence":["NOR/EPI = 21.21 (> 9, well above URL 7)","EPI = 0.74 \u00b5mol/mol (near or below LRL 0.76)"],"rationale":"Differs from acute sympathetic overdrive \u2014 sustained nerve-terminal activity outlasts adrenal medulla reserve."}],"neighbors":[{"id":"SOVOPSYN07254","similarity":0.8879,"score":13.0,"tier":"T1","phenotype":"Burnout","trajectory":"stable","sex":"M","age":51.8},{"id":"SOVOPSYN01011","similarity":0.816,"score":10.5,"tier":"T1","phenotype":"Burnout","trajectory":"stable","sex":"M","age":42.5},{"id":"SOVOPSYN05956","similarity":0.8002,"score":17.9,"tier":"T2","phenotype":"Burnout","trajectory":"stable","sex":"M","age":45.3},{"id":"SOVOPSYN01148","similarity":0.7931,"score":20.6,"tier":"T2","phenotype":"Exhaustion","trajectory":"recovery","sex":"F","age":46.8},{"id":"SOVOPSYN06190","similarity":0.7839,"score":17.2,"tier":"T2","phenotype":"Burnout","trajectory":"stable","sex":"F","age":38.9}],"counterfactual":{"current_score":10.6,"current_tier":"T1","next_tier_below":null,"sensitivities":[{"marker":"m1","label":"Morning cortisol (m1)","current":8.425,"d_score":1.0,"abs_importance":1.0},{"marker":"m2","label":"Cortisol +30 min (m2)","current":9.982,"d_score":-0.7,"abs_importance":0.7},{"marker":"epi","label":"Adrenaline","current":0.739,"d_score":-0.4,"abs_importance":0.4},{"marker":"dhea","label":"DHEA","current":0.914,"d_score":-0.3,"abs_importance":0.3},{"marker":"nor","label":"Noradrenaline","current":15.668,"d_score":0.3,"abs_importance":0.3}],"counterfactuals":[]},"embedding":{"x":-1.3888,"y":0.8835},"expected_tier":"T3"}