{"id":"SOVOPSYN08420","lab_id":"99455365144","sex":"M","age":37.6,"dob":"1988-05-28","phenotype_baseline":"Healthy","phenotype_target":"Healthy","trajectory":"stable","trajectory_strength":0.0,"enrollment_date":"2025-03-26T00:00:00","n_visits_attended":12,"n_visits_with_data":10,"visit_span_days":338,"latest_visit":{"visit_num":10,"days":272,"date":"2025-12-23","biomarkers":{"m1":18.4712,"m2":31.4581,"m3":1.9492,"m4":1.5544,"m5":0.9973,"car_pct":70.3086,"aucg":103.2631,"dcs":-1.0419,"dhea":1.0572,"cor_dhea":17.4726,"da":165.7776,"dopac":2.5871,"hva":3.0301,"nor":26.516,"epi":2.332,"vma":2.267,"mhpg":0.6917,"nor_epi":11.3705,"hva_vma":1.3366,"ser":50.8306,"hiaa":2.223,"hiaa_ser":0.0437,"da_ser":3.2614,"creatinine":79.9322},"result":{"score_formula":9.2,"score_displayed_patient":9.2,"tier_formula":"T1","tier_final":"T1","hpa_score":1.0,"adrenal_score":49.2,"nt_cat_score":6.2,"nt_mon_score":0.0,"nt_score":3.4,"car_pen":0.0,"m3_pen":0.0,"aucg_pen":0.0,"m1_pen":4.8,"dcs_pen":0.0,"dhea_pen":0.0,"cor_dhea_pen":81.9,"reactive_buffer":false,"da_pen":0.0,"nor_pen":0.0,"epi_pen":0.0,"nor_epi_pen":20.8,"ser_pen":0.0,"hiaa_ser_pen":0.0,"da_ser_pen":0.0,"applied_rules":[],"rule_details":[],"phenotype_flags":[],"flag_details":[],"suggested_phase":4,"phase_rationale":"adrenal-axis recovery focus","insights":[{"axis":"Adrenal","severity":"high","title":"Cortisol is dominating DHEA","body":"The catabolic-to-anabolic ratio is well above the upper reference limit \u2014 characteristic of chronic allostatic load."},{"axis":"Neurotransmitter","severity":"moderate","title":"Sympathetic dominance signature","body":"Noradrenaline is elevated relative to adrenaline \u2014 a chronic vigilance pattern."}]}},"trajectory_data":[{"visit":1,"days":0,"month":0.0,"date":"2025-03-26","score":7.7,"tier":"T1","hpa":0.3,"adrenal":45.6,"nt":1.8},{"visit":2,"days":20,"month":0.67,"date":"2025-04-15","score":6.7,"tier":"T1","hpa":0.0,"adrenal":35.6,"nt":3.3},{"visit":3,"days":61,"month":2.03,"date":"2025-05-26","score":6.2,"tier":"T1","hpa":0.0,"adrenal":28.9,"nt":4.7},{"visit":4,"days":80,"month":2.67,"date":"2025-06-14","score":9.0,"tier":"T1","hpa":0.0,"adrenal":52.3,"nt":2.9},{"visit":5,"days":119,"month":3.97,"date":"2025-07-23","score":7.9,"tier":"T1","hpa":0.0,"adrenal":39.4,"nt":5.1},{"visit":6,"days":152,"month":5.07,"date":"2025-08-25","score":6.1,"tier":"T1","hpa":0.0,"adrenal":32.5,"nt":3.0},{"visit":7,"days":180,"month":6.0,"date":"2025-09-22","score":7.1,"tier":"T1","hpa":0.0,"adrenal":41.4,"nt":2.2},{"visit":10,"days":272,"month":9.07,"date":"2025-12-23","score":9.2,"tier":"T1","hpa":1.0,"adrenal":49.2,"nt":3.4}],"percentiles":{"m1":84.3,"m2":82.7,"m3":8.9,"m4":29.9,"m5":48.9,"car_pct":62.0,"aucg":68.0,"dcs":16.9,"dhea":50.0,"cor_dhea":75.5,"da":52.4,"dopac":79.9,"hva":83.1,"nor":65.5,"epi":39.6,"vma":93.0,"mhpg":27.9,"nor_epi":69.0,"hva_vma":33.6,"ser":39.9,"hiaa":72.6,"hiaa_ser":76.0,"da_ser":64.5,"creatinine":11.3},"score_percentile":50.0,"patterns":[{"id":"HEALTHY_REACTIVITY","name":"Healthy stress reactivity","tone":"positive","summary":"Robust CAR, well-stocked DHEA, no triggered rules \u2014 the stress system is functioning as designed.","evidence":["CAR = 70% (in NR 50\u2013120)","DHEA = 1.06 nmol/L (mid\u2013high range)"]}],"neighbors":[{"id":"SOVOPSYN03600","similarity":0.7864,"score":6.0,"tier":"T1","phenotype":"EarlyBurnout","trajectory":"recovery","sex":"M","age":43.7},{"id":"SOVOPSYN05320","similarity":0.7667,"score":14.6,"tier":"T3","phenotype":"AcuteStress","trajectory":"stable","sex":"F","age":43.5},{"id":"SOVOPSYN03441","similarity":0.7488,"score":3.8,"tier":"T1","phenotype":"AcuteStress","trajectory":"recovery","sex":"F","age":27.5},{"id":"SOVOPSYN08530","similarity":0.7347,"score":13.6,"tier":"T3","phenotype":"AcuteStress","trajectory":"stable","sex":"M","age":44.1},{"id":"SOVOPSYN01479","similarity":0.7237,"score":5.5,"tier":"T1","phenotype":"EarlyBurnout","trajectory":"recovery","sex":"F","age":54.4}],"counterfactual":{"current_score":9.2,"current_tier":"T1","next_tier_below":null,"sensitivities":[{"marker":"m1","label":"Morning cortisol (m1)","current":18.471,"d_score":1.0,"abs_importance":1.0},{"marker":"dhea","label":"DHEA","current":1.057,"d_score":-0.5,"abs_importance":0.5},{"marker":"nor","label":"Noradrenaline","current":26.516,"d_score":0.2,"abs_importance":0.2},{"marker":"epi","label":"Adrenaline","current":2.332,"d_score":-0.1,"abs_importance":0.1},{"marker":"m2","label":"Cortisol +30 min (m2)","current":31.458,"d_score":0.0,"abs_importance":0.0}],"counterfactuals":[]},"embedding":{"x":1.2826,"y":-0.359},"expected_tier":"T1"}