{"id":"SOVOPSYN05567","lab_id":"99502717649","sex":"F","age":36.4,"dob":"1989-08-15","phenotype_baseline":"Burnout","phenotype_target":"Burnout","trajectory":"stable","trajectory_strength":0.0,"enrollment_date":"2025-02-06T00:00:00","n_visits_attended":12,"n_visits_with_data":12,"visit_span_days":337,"latest_visit":{"visit_num":12,"days":337,"date":"2026-01-09","biomarkers":{"m1":9.1126,"m2":8.231,"m3":4.5016,"m4":3.3167,"m5":2.7866,"car_pct":-9.674,"aucg":68.646,"dcs":-0.3979,"dhea":0.8509,"cor_dhea":10.7094,"da":102.6247,"dopac":2.5006,"hva":1.9506,"nor":22.2966,"epi":3.584,"vma":1.6119,"mhpg":1.0629,"nor_epi":6.2212,"hva_vma":1.2101,"ser":39.91,"hiaa":1.8895,"hiaa_ser":0.0473,"da_ser":2.5714,"creatinine":75.418},"result":{"score_formula":10.8,"score_displayed_patient":10.8,"tier_formula":"T1","tier_final":"T1","hpa_score":16.6,"adrenal_score":20.2,"nt_cat_score":1.2,"nt_mon_score":0.0,"nt_score":0.7,"car_pen":66.3,"m3_pen":0.0,"aucg_pen":0.0,"m1_pen":0.0,"dcs_pen":0.0,"dhea_pen":0.0,"cor_dhea_pen":33.6,"reactive_buffer":false,"da_pen":5.0,"nor_pen":0.0,"epi_pen":0.0,"nor_epi_pen":0.0,"ser_pen":0.0,"hiaa_ser_pen":0.0,"da_ser_pen":0.0,"applied_rules":[],"rule_details":[],"phenotype_flags":[],"flag_details":[],"suggested_phase":3,"phase_rationale":"DA substrate restoration \u2014 SER is adequate","insights":[{"axis":"HPA","severity":"moderate","title":"Your morning cortisol surge is muted","body":"The normal post-waking cortisol rise is small. Often linked to chronic load, light exposure timing, or sleep architecture."},{"axis":"Adrenal","severity":"high","title":"Cortisol is dominating DHEA","body":"The catabolic-to-anabolic ratio is well above the upper reference limit \u2014 characteristic of chronic allostatic load."},{"axis":"Neurotransmitter","severity":"high","title":"Dopamine output is below the reference floor","body":"Reduced dopamine throughput correlates with motivation, focus, and reward-seeking changes."}]}},"trajectory_data":[{"visit":1,"days":0,"month":0.0,"date":"2025-02-06","score":12.5,"tier":"T1","hpa":16.4,"adrenal":25.8,"nt":3.1},{"visit":3,"days":61,"month":2.03,"date":"2025-04-08","score":14.5,"tier":"T1","hpa":16.7,"adrenal":26.9,"nt":7.4},{"visit":4,"days":105,"month":3.5,"date":"2025-05-22","score":10.9,"tier":"T1","hpa":15.9,"adrenal":15.6,"nt":3.5},{"visit":5,"days":115,"month":3.83,"date":"2025-06-01","score":12.3,"tier":"T3","hpa":17.9,"adrenal":20.1,"nt":3.1},{"visit":6,"days":150,"month":5.0,"date":"2025-07-06","score":18.7,"tier":"T2","hpa":32.0,"adrenal":8.7,"nt":7.6},{"visit":7,"days":167,"month":5.57,"date":"2025-07-23","score":16.7,"tier":"T2","hpa":17.0,"adrenal":24.0,"nt":13.6},{"visit":8,"days":221,"month":7.37,"date":"2025-09-15","score":11.9,"tier":"T1","hpa":16.5,"adrenal":17.9,"nt":4.5},{"visit":9,"days":239,"month":7.97,"date":"2025-10-03","score":16.6,"tier":"T2","hpa":17.2,"adrenal":20.7,"nt":14.3},{"visit":10,"days":263,"month":8.77,"date":"2025-10-27","score":15.2,"tier":"T2","hpa":16.6,"adrenal":34.9,"nt":6.2},{"visit":12,"days":337,"month":11.23,"date":"2026-01-09","score":10.8,"tier":"T1","hpa":16.6,"adrenal":20.2,"nt":0.7}],"percentiles":{"m1":24.2,"m2":14.3,"m3":66.8,"m4":83.9,"m5":98.6,"car_pct":5.6,"aucg":23.3,"dcs":82.5,"dhea":34.9,"cor_dhea":38.2,"da":14.3,"dopac":76.7,"hva":27.4,"nor":48.4,"epi":77.2,"vma":56.1,"mhpg":86.3,"nor_epi":20.4,"hva_vma":21.5,"ser":17.9,"hiaa":46.4,"hiaa_ser":83.1,"da_ser":32.5,"creatinine":6.4},"score_percentile":56.7}