{"id":"SOVOPSYN05737","lab_id":"99268367285","sex":"F","age":46.7,"dob":"1979-06-25","phenotype_baseline":"Burnout","phenotype_target":"Burnout","trajectory":"stable","trajectory_strength":0.0,"enrollment_date":"2025-04-05T00:00:00","n_visits_attended":12,"n_visits_with_data":10,"visit_span_days":343,"latest_visit":{"visit_num":12,"days":343,"date":"2026-03-14","biomarkers":{"m1":6.2633,"m2":9.8324,"m3":4.798,"m4":3.0373,"m5":2.7172,"car_pct":56.9854,"aucg":71.9574,"dcs":-0.246,"dhea":0.9009,"cor_dhea":6.9525,"da":131.9745,"dopac":1.269,"hva":2.4854,"nor":30.658,"epi":2.3497,"vma":1.8395,"mhpg":0.6487,"nor_epi":13.0477,"hva_vma":1.3511,"ser":46.1005,"hiaa":2.1928,"hiaa_ser":0.0476,"da_ser":2.8628,"creatinine":107.8382},"result":{"score_formula":3.1,"score_displayed_patient":3.1,"tier_formula":"T1","tier_final":"T1","hpa_score":0.0,"adrenal_score":4.1,"nt_cat_score":11.5,"nt_mon_score":0.0,"nt_score":6.3,"car_pen":0.0,"m3_pen":0.0,"aucg_pen":0.0,"m1_pen":0.0,"dcs_pen":0.0,"dhea_pen":0.0,"cor_dhea_pen":6.8,"reactive_buffer":false,"da_pen":0.0,"nor_pen":9.5,"epi_pen":0.0,"nor_epi_pen":28.8,"ser_pen":0.0,"hiaa_ser_pen":0.0,"da_ser_pen":0.0,"applied_rules":[],"rule_details":[],"phenotype_flags":["NOCTURNAL_HYPERCORTISOLISM_ISOLATED"],"flag_details":[{"flag":"NOCTURNAL_HYPERCORTISOLISM_ISOLATED","note":"Isolated nocturnal cortisol excess with otherwise-preserved diurnal architecture"}],"suggested_phase":6,"phase_rationale":"stable \u2014 maintenance","insights":[{"axis":"Neurotransmitter","severity":"moderate","title":"Sympathetic dominance signature","body":"Noradrenaline is elevated relative to adrenaline \u2014 a chronic vigilance pattern."},{"axis":"HPA","severity":"moderate","title":"Night-time cortisol stays elevated","body":"Daytime rhythm is preserved but evening/night cortisol does not fully drop. Often linked to sleep, late stimulants, or rumination."}]}},"trajectory_data":[{"visit":1,"days":0,"month":0.0,"date":"2025-04-05","score":2.7,"tier":"T1","hpa":0.0,"adrenal":5.4,"nt":4.7},{"visit":2,"days":20,"month":0.67,"date":"2025-04-25","score":0.7,"tier":"T1","hpa":0.0,"adrenal":2.9,"nt":0.6},{"visit":3,"days":45,"month":1.5,"date":"2025-05-20","score":1.2,"tier":"T1","hpa":0.0,"adrenal":4.1,"nt":1.5},{"visit":5,"days":123,"month":4.1,"date":"2025-08-06","score":3.2,"tier":"T1","hpa":0.0,"adrenal":5.9,"nt":5.9},{"visit":6,"days":147,"month":4.9,"date":"2025-08-30","score":2.2,"tier":"T1","hpa":0.0,"adrenal":7.8,"nt":2.6},{"visit":7,"days":195,"month":6.5,"date":"2025-10-17","score":4.3,"tier":"T1","hpa":3.3,"adrenal":4.6,"nt":5.3},{"visit":8,"days":216,"month":7.2,"date":"2025-11-07","score":2.5,"tier":"T1","hpa":0.0,"adrenal":5.0,"nt":4.5},{"visit":9,"days":255,"month":8.5,"date":"2025-12-16","score":0.5,"tier":"T1","hpa":0.0,"adrenal":1.8,"nt":0.5},{"visit":12,"days":343,"month":11.43,"date":"2026-03-14","score":3.1,"tier":"T1","hpa":0.0,"adrenal":4.1,"nt":6.3}],"percentiles":{"m1":12.5,"m2":17.2,"m3":74.0,"m4":78.3,"m5":98.2,"car_pct":47.6,"aucg":27.0,"dcs":90.0,"dhea":38.3,"cor_dhea":9.5,"da":27.0,"dopac":15.3,"hva":58.2,"nor":77.2,"epi":40.2,"vma":75.6,"mhpg":21.7,"nor_epi":77.6,"hva_vma":34.8,"ser":29.3,"hiaa":70.7,"hiaa_ser":83.6,"da_ser":46.8,"creatinine":76.3},"score_percentile":16.7,"patterns":[{"id":"NOCTURNAL_HYPERCORTISOLISM","name":"Isolated nocturnal cortisol excess","tone":"neutral","summary":"Daytime rhythm is preserved but evening cortisol fails to fall \u2014 sleep, late stimulants or rumination.","evidence":["m5 = 2.72 nmol/L (> URL 1.4)","daytime architecture preserved (CAR, AUCg, DCS, m1 all in NR)"]}],"neighbors":[{"id":"SOVOPSYN09312","similarity":0.8784,"score":5.6,"tier":"T3","phenotype":"EarlyBurnout","trajectory":"decline","sex":"F","age":26.5},{"id":"SOVOPSYN08949","similarity":0.8697,"score":11.3,"tier":"T1","phenotype":"EarlyBurnout","trajectory":"decline","sex":"M","age":29.3},{"id":"SOVOPSYN08505","similarity":0.839,"score":6.3,"tier":"T1","phenotype":"Burnout","trajectory":"recovery","sex":"F","age":50.8},{"id":"SOVOPSYN05956","similarity":0.8359,"score":17.9,"tier":"T2","phenotype":"Burnout","trajectory":"stable","sex":"M","age":45.3},{"id":"SOVOPSYN01556","similarity":0.8318,"score":11.0,"tier":"T1","phenotype":"Burnout","trajectory":"stable","sex":"F","age":33.3}],"embedding":{"x":-1.2578,"y":1.522},"expected_tier":"T3"}