{"id":"SOVOPSYN05369","lab_id":"99192955057","sex":"F","age":50.0,"dob":"1975-11-30","phenotype_baseline":"Exhaustion","phenotype_target":"EarlyBurnout","trajectory":"recovery","trajectory_strength":0.623,"enrollment_date":"2025-02-14T00:00:00","n_visits_attended":10,"n_visits_with_data":10,"visit_span_days":277,"latest_visit":{"visit_num":10,"days":277,"date":"2025-11-18","biomarkers":{"m1":4.9573,"m2":5.9811,"m3":4.4089,"m4":2.1469,"m5":0.8798,"car_pct":20.652,"aucg":51.8327,"dcs":-0.2844,"dhea":0.419,"cor_dhea":11.8313,"da":138.0685,"dopac":1.469,"hva":2.2269,"nor":12.2078,"epi":1.7698,"vma":1.1754,"mhpg":0.6644,"nor_epi":6.8978,"hva_vma":1.8946,"ser":41.7172,"hiaa":1.6139,"hiaa_ser":0.0387,"da_ser":3.3096,"creatinine":107.6889},"result":{"score_formula":8.7,"score_displayed_patient":8.7,"tier_formula":"T1","tier_final":"T1","hpa_score":8.3,"adrenal_score":33.4,"nt_cat_score":0.0,"nt_mon_score":0.0,"nt_score":0.0,"car_pen":32.6,"m3_pen":0.0,"aucg_pen":0.0,"m1_pen":0.7,"dcs_pen":0.0,"dhea_pen":20.9,"cor_dhea_pen":41.7,"reactive_buffer":false,"da_pen":0.0,"nor_pen":0.0,"epi_pen":0.0,"nor_epi_pen":0.0,"ser_pen":0.0,"hiaa_ser_pen":0.0,"da_ser_pen":0.0,"applied_rules":[],"rule_details":[],"phenotype_flags":[],"flag_details":[],"suggested_phase":4,"phase_rationale":"adrenal-axis recovery focus","insights":[{"axis":"Adrenal","severity":"high","title":"DHEA reserve is low","body":"DHEA is the body's anabolic counter to cortisol. Low values suggest the adrenal cortex is running on empty."},{"axis":"Adrenal","severity":"high","title":"Cortisol is dominating DHEA","body":"The catabolic-to-anabolic ratio is well above the upper reference limit \u2014 characteristic of chronic allostatic load."}]}},"trajectory_data":[{"visit":1,"days":0,"month":0.0,"date":"2025-02-14","score":18.3,"tier":"T2","hpa":16.9,"adrenal":54.7,"nt":6.1},{"visit":2,"days":15,"month":0.5,"date":"2025-03-01","score":15.9,"tier":"T2","hpa":15.6,"adrenal":45.8,"nt":5.1},{"visit":5,"days":126,"month":4.2,"date":"2025-06-20","score":14.6,"tier":"T1","hpa":16.6,"adrenal":31.9,"nt":5.9},{"visit":6,"days":138,"month":4.6,"date":"2025-07-02","score":15.7,"tier":"T2","hpa":12.7,"adrenal":51.7,"nt":5.6},{"visit":7,"days":190,"month":6.33,"date":"2025-08-23","score":15.0,"tier":"T1","hpa":11.7,"adrenal":62.2,"nt":0.9},{"visit":8,"days":223,"month":7.43,"date":"2025-09-25","score":13.6,"tier":"T1","hpa":8.9,"adrenal":62.6,"nt":0.6},{"visit":10,"days":277,"month":9.23,"date":"2025-11-18","score":8.7,"tier":"T1","hpa":8.3,"adrenal":33.4,"nt":0.0}],"percentiles":{"m1":9.2,"m2":10.5,"m3":64.3,"m4":54.5,"m5":38.9,"car_pct":19.6,"aucg":13.4,"dcs":88.2,"dhea":13.2,"cor_dhea":47.1,"da":31.0,"dopac":21.7,"hva":42.9,"nor":9.4,"epi":22.8,"vma":18.3,"mhpg":23.7,"nor_epi":28.0,"hva_vma":79.2,"ser":20.9,"hiaa":26.9,"hiaa_ser":61.4,"da_ser":66.2,"creatinine":76.0},"score_percentile":47.9}