{"id":"SOVOPSYN09714","lab_id":"99281421476","sex":"F","age":28.5,"dob":"1997-08-14","phenotype_baseline":"Exhaustion","phenotype_target":"EarlyBurnout","trajectory":"recovery","trajectory_strength":0.911,"enrollment_date":"2025-03-20T00:00:00","n_visits_attended":12,"n_visits_with_data":10,"visit_span_days":323,"latest_visit":{"visit_num":12,"days":323,"date":"2026-02-06","biomarkers":{"m1":16.9031,"m2":27.0894,"m3":3.325,"m4":3.1871,"m5":1.3168,"car_pct":60.2629,"aucg":107.9744,"dcs":-0.9196,"dhea":1.4749,"cor_dhea":11.4606,"da":165.5799,"dopac":3.2722,"hva":2.6346,"nor":33.8367,"epi":5.0554,"vma":1.8906,"mhpg":0.2932,"nor_epi":6.6931,"hva_vma":1.3935,"ser":45.6415,"hiaa":2.4012,"hiaa_ser":0.0526,"da_ser":3.6278,"creatinine":72.2099},"result":{"score_formula":5.3,"score_displayed_patient":5.3,"tier_formula":"T1","tier_final":"T1","hpa_score":0.0,"adrenal_score":23.4,"nt_cat_score":8.0,"nt_mon_score":0.4,"nt_score":4.6,"car_pen":0.0,"m3_pen":0.0,"aucg_pen":0.0,"m1_pen":0.0,"dcs_pen":0.0,"dhea_pen":0.0,"cor_dhea_pen":39.0,"reactive_buffer":false,"da_pen":0.0,"nor_pen":20.8,"epi_pen":11.7,"nor_epi_pen":0.0,"ser_pen":0.0,"hiaa_ser_pen":0.0,"da_ser_pen":1.8,"applied_rules":[],"rule_details":[],"phenotype_flags":[],"flag_details":[],"suggested_phase":4,"phase_rationale":"adrenal-axis recovery focus","insights":[{"axis":"Adrenal","severity":"high","title":"Cortisol is dominating DHEA","body":"The catabolic-to-anabolic ratio is well above the upper reference limit \u2014 characteristic of chronic allostatic load."}]}},"trajectory_data":[{"visit":1,"days":0,"month":0.0,"date":"2025-03-20","score":19.9,"tier":"T2","hpa":24.9,"adrenal":34.5,"nt":8.9},{"visit":5,"days":105,"month":3.5,"date":"2025-07-03","score":20.6,"tier":"T2","hpa":39.5,"adrenal":10.7,"nt":3.0},{"visit":7,"days":175,"month":5.83,"date":"2025-09-11","score":11.2,"tier":"T1","hpa":13.9,"adrenal":26.3,"nt":2.6},{"visit":8,"days":207,"month":6.9,"date":"2025-10-13","score":13.3,"tier":"T1","hpa":11.6,"adrenal":31.4,"nt":8.5},{"visit":9,"days":231,"month":7.7,"date":"2025-11-06","score":8.3,"tier":"T1","hpa":0.0,"adrenal":32.9,"nt":8.4},{"visit":11,"days":286,"month":9.53,"date":"2025-12-31","score":12.1,"tier":"T3","hpa":9.2,"adrenal":46.1,"nt":2.8},{"visit":12,"days":323,"month":10.77,"date":"2026-02-06","score":5.3,"tier":"T1","hpa":0.0,"adrenal":23.4,"nt":4.6}],"percentiles":{"m1":78.0,"m2":72.8,"m3":32.6,"m4":81.4,"m5":67.2,"car_pct":51.0,"aucg":72.3,"dcs":26.5,"dhea":80.0,"cor_dhea":44.3,"da":52.2,"dopac":93.8,"hva":66.4,"nor":84.1,"epi":94.0,"vma":79.0,"mhpg":1.0,"nor_epi":25.8,"hva_vma":39.3,"ser":28.3,"hiaa":82.4,"hiaa_ser":90.0,"da_ser":77.3,"creatinine":4.3},"score_percentile":31.8}