{"id":"SOVOPSYN02655","lab_id":"99361384856","sex":"M","age":47.0,"dob":"1978-11-11","phenotype_baseline":"EarlyBurnout","phenotype_target":"Healthy","trajectory":"recovery","trajectory_strength":0.897,"enrollment_date":"2025-03-28T00:00:00","n_visits_attended":9,"n_visits_with_data":9,"visit_span_days":241,"latest_visit":{"visit_num":9,"days":241,"date":"2025-11-24","biomarkers":{"m1":19.7532,"m2":33.8685,"m3":4.9256,"m4":2.3499,"m5":1.0732,"car_pct":71.4578,"aucg":129.3647,"dcs":-1.1565,"dhea":0.9676,"cor_dhea":20.4151,"da":184.4779,"dopac":3.251,"hva":2.4055,"nor":22.4166,"epi":2.4658,"vma":1.53,"mhpg":0.5911,"nor_epi":9.0911,"hva_vma":1.5722,"ser":64.4109,"hiaa":3.0404,"hiaa_ser":0.0472,"da_ser":2.8641,"creatinine":85.029},"result":{"score_formula":11.5,"score_displayed_patient":11.5,"tier_formula":"T1","tier_final":"T1","hpa_score":4.0,"adrenal_score":60.0,"nt_cat_score":3.0,"nt_mon_score":0.0,"nt_score":1.6,"car_pen":0.0,"m3_pen":0.0,"aucg_pen":10.1,"m1_pen":9.3,"dcs_pen":1.0,"dhea_pen":0.0,"cor_dhea_pen":100.0,"reactive_buffer":false,"da_pen":0.0,"nor_pen":0.0,"epi_pen":0.0,"nor_epi_pen":10.0,"ser_pen":0.0,"hiaa_ser_pen":0.0,"da_ser_pen":0.0,"applied_rules":[],"rule_details":[],"phenotype_flags":[],"flag_details":[],"suggested_phase":4,"phase_rationale":"adrenal-axis recovery focus","insights":[{"axis":"HPA","severity":"high","title":"Your daily cortisol output is elevated","body":"Sustained cortisol exposure across the day has metabolic and cardiovascular consequences if prolonged."},{"axis":"Adrenal","severity":"high","title":"Cortisol is dominating DHEA","body":"The catabolic-to-anabolic ratio is well above the upper reference limit \u2014 characteristic of chronic allostatic load."},{"axis":"Neurotransmitter","severity":"moderate","title":"Sympathetic dominance signature","body":"Noradrenaline is elevated relative to adrenaline \u2014 a chronic vigilance pattern."}]}},"trajectory_data":[{"visit":1,"days":0,"month":0.0,"date":"2025-03-28","score":8.6,"tier":"T1","hpa":0.8,"adrenal":37.9,"nt":6.4},{"visit":3,"days":63,"month":2.1,"date":"2025-05-30","score":11.3,"tier":"T1","hpa":0.5,"adrenal":52.6,"nt":8.0},{"visit":4,"days":91,"month":3.03,"date":"2025-06-27","score":13.0,"tier":"T3","hpa":3.2,"adrenal":60.0,"nt":6.5},{"visit":6,"days":137,"month":4.57,"date":"2025-08-12","score":11.5,"tier":"T1","hpa":5.5,"adrenal":60.0,"nt":0.0},{"visit":9,"days":241,"month":8.03,"date":"2025-11-24","score":11.5,"tier":"T1","hpa":4.0,"adrenal":60.0,"nt":1.6}],"percentiles":{"m1":88.4,"m2":86.0,"m3":76.8,"m4":61.5,"m5":54.2,"car_pct":63.0,"aucg":85.7,"dcs":10.5,"dhea":42.9,"cor_dhea":83.6,"da":69.3,"dopac":93.6,"hva":53.6,"nor":48.9,"epi":44.5,"vma":48.0,"mhpg":15.6,"nor_epi":51.2,"hva_vma":56.4,"ser":75.1,"hiaa":97.4,"hiaa_ser":82.9,"da_ser":46.9,"creatinine":18.8},"score_percentile":59.7}